cloudsight/__init__.py
cloudsight/api.py
cloudsight/auth.py
cloudsight/errors.py
cloudsight-0.9.2.dist-info/DESCRIPTION.rst
cloudsight-0.9.2.dist-info/METADATA
cloudsight-0.9.2.dist-info/RECORD
cloudsight-0.9.2.dist-info/WHEEL
cloudsight-0.9.2.dist-info/metadata.json
cloudsight-0.9.2.dist-info/top_level.txt
cloudsight-0.9.2.dist-info/zip-safe
