Metadata-Version: 1.1
Name: cloudsight
Version: 0.9.2
Summary: CloudSight API library for Python
Home-page: https://github.com/cloudsight/cloudsight-python
Author: CloudSight
Author-email: miGlanz@gmail.com
License: MIT
Keywords: cloudsight library
Platform: UNKNOWN
Classifier: Development Status :: 4 - Beta
Classifier: Topic :: Software Development :: Libraries
Classifier: License :: OSI Approved :: MIT License
Classifier: Operating System :: OS Independent
Classifier: Programming Language :: Python
Classifier: Programming Language :: Python :: 2
Classifier: Programming Language :: Python :: 2.7
Classifier: Programming Language :: Python :: 3
Classifier: Programming Language :: Python :: 3.3
Classifier: Programming Language :: Python :: 3.4
Classifier: Programming Language :: Python :: 3.5
